fastdebug/__init__.py
fastdebug/_nbdev.py
fastdebug/torch.py
fastdebug/error/__init__.py
fastdebug/error/fastai.py
fastdebug/error/torch.py
fastdebug/fastai/__init__.py
fastdebug/fastai/dataloader.py
fastdebug/fastai/datasets.py
fastdebug/fastai/learner.py
fastdebug/fastai/transform.py
fastdebug-0.1.4.dist-info/METADATA
fastdebug-0.1.4.dist-info/RECORD
fastdebug-0.1.4.dist-info/WHEEL
fastdebug-0.1.4.dist-info/entry_points.txt
fastdebug-0.1.4.dist-info/top_level.txt
