Metadata-Version: 2.1
Name: fastdebug
Version: 0.1.4
Summary: A library that improves the debugging messages for Pytorch and fastai
Home-page: https://github.com/muellerzr/fastdebug/tree/master/
Author: Zachary Mueller
Author-email: muellerzr@gmail.com
License: Apache Software License 2.0
Keywords: fastai pytorch debugging
Platform: UNKNOWN
Classifier: Development Status :: 3 - Alpha
Classifier: Intended Audience :: Developers
Classifier: Natural Language :: English
Classifier: Programming Language :: Python :: 3.6
Classifier: Programming Language :: Python :: 3.7
Classifier: Programming Language :: Python :: 3.8
Classifier: License :: OSI Approved :: Apache Software License
Requires-Python: >=3.6
Provides-Extra: dev
Requires-Dist: pip
Requires-Dist: packaging
Requires-Dist: torch (>=1.7.0)
Requires-Dist: fastai (>=2.0.0)
Requires-Dist: inflect (>=5.3.0)
Provides-Extra: dev
